ensemble_seg/__init__.py
ensemble_seg/ensemble.py
ensemble_seg-0.3.0.dist-info/LICENSE
ensemble_seg-0.3.0.dist-info/METADATA
ensemble_seg-0.3.0.dist-info/WHEEL
ensemble_seg-0.3.0.dist-info/top_level.txt
ensemble_seg-0.3.0.dist-info/RECORD
