Metadata-Version: 2.1
Name: ensemble_seg
Version: 0.3.0
Summary: Agnostic ensemble algorithm for instance segmentation tasks
Home-page: https://github.com/ainascan/ensemble_seg
Author: Jack Mead
Author-email: jackmead515@gmail.com
Classifier: Development Status :: 3 - Alpha
Classifier: Intended Audience :: Developers
Classifier: License :: OSI Approved :: MIT License
Classifier: Programming Language :: Python :: 3
Classifier: Programming Language :: Python :: 3.6
Classifier: Programming Language :: Python :: 3.7
Classifier: Programming Language :: Python :: 3.8
License-File: LICENSE
Requires-Dist: numpy
Requires-Dist: numba
Requires-Dist: opencv-python
